[
	{
		"Enabled" : true,
		"Name" : "Empower lvl 3 non-Corrupted",
		"Link" : "okometamisinaz",
		"Price": 140,
		"Alert": false
	},
	{
		"Enabled" : true,
		"Name" : "Empower lvl 2 non-Corrupted",
		"Link" : "tetinokimekeha",
		"Price": 20,
		"Alert": false
	},
	{
		"Enabled" : true,
		"Name" : "Empower lvl 1 non-Corrupted",
		"Link" : "tutikomikusiha",
		"Price": 6,
		"Alert": false
	},
	{
		"Enabled" : true,
		"Name" : "Pledge of Hands max Spell dmg",
		"Link" : "mosisiyahukiti",
		"Price": 50,
		"Alert": true
	},
	{
		"Enabled" : true,
		"Name"	: "Enlighten lvl 3 Non-Corrupted",
		"Link"	: "moyasaritoruga",
		"Price" : 150,
		"Alert" : false
	},
	{
		"Enabled" : true,
		"Name"	: "Enlighten lvl 2 Non-Corrupted",
		"Link"	: "nisakesoyeikoh",
		"Price" : 22,
		"Alert" : false
	},
	{
		"Enabled" : true,
		"Name"	: "Enlighten lvl 1 Non-Corrupted",
		"Link"	: "nonitasigokite",
		"Price" : 8,
		"Alert" : false
	},
	{
		"Enabled" : true,
		"Name"	: "Enhance lvl 3 Non-Corrupted",
		"Link"	: "asasosiwouoaha",
		"Price" : 166,
		"Alert" : false
	},
	{
		"Enabled" : true,
		"Name"	: "Enhance lvl 2 Non-Corrupted",
		"Link"	: "umayetiokaroto",
		"Price" : 7,
		"Alert" : false
	},
	{
		"Enabled" : true,
		"Name"	: "Enhance lvl 4",
		"Link"	: "iriniwomakohim",
		"Price" : 581,
		"Alert" : false
	},
	{
		"Enabled" : true,
		"Name"	: "Empower lvl 4",
		"Link"	: "ohamidohamaniy",
		"Price" : 1162,
		"Alert" : false
	},
	{
		"Enabled" : true,
		"Name"	: "Enlighten lvl 4",
		"Link"	: "haraumhamaugok",
		"Price" : 830,
		"Alert" : false
	},
	{
		"Enabled" : true,
		"Name"	: "Voll's Devotion",
		"Link"	: "asariamidonazu",
		"Price" : 1245,
		"Alert" : false
	},
	{
		"Enabled" : true,
		"Name"	: "Voll's Devotion non-Corrupted",
		"Link"	: "omomkasukobiki",
		"Price" : 1909,
		"Alert" : false
	},
	{
		"Enabled" : true,
		"Name"	: "Void Battery",
		"Link"	: "ugahasiritahon",
		"Price" : 332,
		"Alert" : false
	},
	{
		"Enabled" : true,
		"Name"	: "Void Battery - Unidentified",
		"Link"	: "ohitahahorunor",
		"Price" : 375,
		"Alert" : false
	},
	{
		"Enabled" : true,
		"Name"	: "Rat's Nest",
		"Link"	: "ototamokeninoh",
		"Price" : 83,
		"Alert" : false
	},
	{
		"Enabled" : true,
		"Name"	: "Rat's Nest - Unidentified",
		"Link"	: "hayaunonasubeh",
		"Price" : 125,
		"Alert" : false
	},
	{
		"Enabled" : true,
		"Name"	: "Windripper",
		"Link"	: "howariitohewak",
		"Price" : 60,
		"Alert" : false
	},
	{
		"Enabled" : true,
		"Name"	: "Windripper - Unidentified",
		"Link"	: "imonowakatonas",
		"Price" : 125,
		"Alert" : false
	},
	{
		"Enabled" : true,
		"Name"	: "Vessel of Vinktar Topaz Flask",
		"Link"	: "sihitenimaruki",
		"Price" : 125,
		"Alert" : false
	},
	{
		"Enabled" : true,
		"Name"	: "Maligaro's Virtuosity Deerskin Gloves",
		"Link"	: "amikitonohoato",
		"Price" : 125,
		"Alert" : false
	},
	{
		"Enabled" : true,
		"Name"	: "Maligaro's Virtuosity Deerskin Gloves - Unidentified",
		"Link"	: "areteturimotar",
		"Price" : 166,
		"Alert" : false
	},
	{
		"Enabled" : true,
		"Name"	: "Agnerod North Imperial Staff",
		"Link"	: "ohonitamagonas",
		"Price" : 40,
		"Alert" : false
	},
	{
		"Enabled" : true,
		"Name"	: "Shavronne's Wrappings Occultist's Vestment",
		"Link"	: "itohubauhosiha",
		"Price" : 400,
		"Alert" : false
	},
	{
		"Enabled" : true,
		"Name"	: "Shavronne's Wrappings Occultist's Vestment - Unidentified",
		"Link"	: "hitasitotauase",
		"Price" : 581,
		"Alert" : false
	},
	{
		"Enabled" : true,
		"Name"	: "Brinerot Whalers Trapper Boots",
		"Link"	: "amorinazunotar",
		"Price" : 400,
		"Alert" : false
	},
	{
		"Enabled" : true,
		"Name"	: "Voltaxic Rift Spine Bow",
		"Link"	: "edukomerakomom",
		"Price" : 83,
		"Alert" : false
	},
	{
		"Enabled" : true,
		"Name"	: "Voltaxic Rift Spine Bow - Unidentified",
		"Link"	: "imakonohinitan",
		"Price" : 125,
		"Alert" : false
	},
	{
		"Enabled" : true,
		"Name"	: "Gifts from Above Diamond Ring",
		"Link"	: "uhamounatetoka",
		"Price" : 120,
		"Alert" : false
	},
	{
		"Enabled" : true,
		"Name"	: "6L Unique Chest Armour non-Corrupted",
		"Link"	: "unuginatimkasi",
		"Price" : 500,
		"Alert" : false
	},
	{
		"Enabled" : true,
		"Name"	: "6L Unique Chest Evasion non-Corrupted",
		"Link"	: "imahariorimita",
		"Price" : 330,
		"Alert" : false
	},
	{
		"Enabled" : true,
		"Name"	: "6L Unique Chest Shield non-Corrupted",
		"Link"	: "ositomaseyuwom",
		"Price" : 330,
		"Alert" : false
	},
	{
		"Enabled" : true,
		"Name"	: "6L 2H Unique Weapon",
		"Link"	: "tetesenasatazi",
		"Price" : 250,
		"Alert" : false
	},
	{
		"Enabled" : true,
		"Name"	: "Bino's Kitchen Knife Slaughter Knife",
		"Link"	: "ohohamougomoko",
		"Price" : 60,
		"Alert" : false
	},
	{
		"Enabled" : true,
		"Name"	: "Bino's Kitchen Knife Slaughter Knife - Unidentified",
		"Link"	: "omahatonomonik",
		"Price" : 83,
		"Alert" : false
	},
	{
		"Enabled" : true,
		"Name"	: "DAGGERDANNY OHLOLOLOLOLOL DAGGER",
		"Link"	: "hasoratudosaur",
		"Price" : 8300,
		"Alert" : false
	},
	{
		"Enabled" : true,
		"Name"	: "DAGGERDANNY OHLOLOLOLOLOL Shield",
		"Link"	: "anokahatenugam",
		"Price" : 830,
		"Alert" : false
	},
	{
		"Enabled" : true,
		"Name"	: "Jewel Crit Life Resi Mana-Leech",
		"Link"	: "hasamomauzimaz",
		"Price" : 830,
		"Alert" : false
	},
	{
		"Enabled" : true,
		"Name"	: "Jewel  Life Resi Crit-Multi Melee-Damage",
		"Link"	: "aterigesahiyam",
		"Price" : 830,
		"Alert" : false
	},
	{
		"Enabled" : true,
		"Name"	: "Jewel  Life Crit Crit-Multi Melee-Damage",
		"Link"	: "medizumakarawa",
		"Price" : 830,
		"Alert" : false
	},
	{
		"Enabled" : true,
		"Name"	: "Atziri's Acuity Vaal Gauntlets",
		"Link"	: "bizunotoririki",
		"Price" : 1660,
		"Alert" : false
	},
	{
		"Enabled" : true,
		"Name"	: "Atziri's Acuity Vaal Gauntlets - Unidentified",
		"Link"	: "bizunotoririki",
		"Price" : 2490,
		"Alert" : false
	},
	{
		"Enabled" : true,
		"Name"	: "Taste of Hate Sapphire Flask",
		"Link"	: "usiyasihutawas",
		"Price" : 166,
		"Alert" : false
	}
]